m3_python_sdk/__init__.py
m3_python_sdk/resources/__init__.py
m3_python_sdk/resources/billing/__init__.py
m3_python_sdk/resources/billing/billing.py
m3_python_sdk/resources/consumption/__init__.py
m3_python_sdk/resources/consumption/adjustment.py
m3_python_sdk/resources/consumption/consumption.py
m3_python_sdk/services/__init__.py
m3_python_sdk/services/s3_client.py
m3_python_sdk/strategies/__init__.py
m3_python_sdk/strategies/abstract_strategy.py
m3_python_sdk/strategies/http.py
m3_python_sdk/strategies/rabbitmq.py
m3_python_sdk/utils/__init__.py
m3_python_sdk/utils/constants.py
m3_python_sdk/utils/exeption.py
m3_python_sdk/utils/file_utils.py
m3_python_sdk/utils/logger.py
maestro_python_sdk-1.1.0.dist-info/LICENSE
maestro_python_sdk-1.1.0.dist-info/METADATA
maestro_python_sdk-1.1.0.dist-info/WHEEL
maestro_python_sdk-1.1.0.dist-info/top_level.txt
maestro_python_sdk-1.1.0.dist-info/RECORD
