Metadata-Version: 2.2
Name: maestro-python-sdk
Version: 1.1.0
Summary: SDK for facilitating the communication with Maestro for all Pythonic components
Author-email: maestrocloudcontrol <support@maestrocontrol.cloud>
License:                                  Apache License
Project-URL: Homepage, https://github.com/Maestro-Cloud-Control/m3-python-sdk
Project-URL: Documentation, https://github.com/Maestro-Cloud-Control/m3-python-sdk/blob/main/README.md
Project-URL: Repository, https://github.com/Maestro-Cloud-Control/m3-python-sdk
Project-URL: Changelog, https://github.com/Maestro-Cloud-Control/m3-python-sdk/blob/main/CHANGELOG.md
Classifier: Programming Language :: Python :: 3
Classifier: License :: OSI Approved :: Apache Software License
Classifier: Operating System :: OS Independent
Requires-Python: >=3.10
License-File: LICENSE
Requires-Dist: pika==1.3.2
Requires-Dist: requests==2.31.0
Requires-Dist: cryptography==41.0.7
Requires-Dist: pycparser==2.21
Requires-Dist: cffi==1.15.1
